[
  {
    "名称": "时游族",
    "原名": "Time Race",
    "类型": "主职",
    "领域": "虚无领域和沉沦领域",
    "初始闪避值": "10",
    "初始生命点": "6",
    "职业物品": "一块怀表或一本手札",
    "希望特性": "时差：花费3希望点，将与已经确定的掷骰结果相关的一个事件暂时“冻结”并设置一个标准倒计时（1）。倒计时结束时，事件继续依照其掷骰结果如常发生。",
    "职业特性": "稳态：你不受紊乱状态和崩解状态的影响。\n时滞：当你进行动作掷骰时，你可以标记2压力点，使得此次动作掷骰不会使得标准倒计时减少。",
    "背景问题": [
      "你是如何思考“沉沦”和“虚无”的？",
      "你是如何看待时间的？",
      "你的职业物品来自过去，还是未来？你是如何获得它的？"
    ],
    "关系问题": [
      "我们在第一次见面的时候，你因为我知道你的一个秘密而有些慌神，那是怎样的一个秘密？你猜测我是如何知道的？",
      "你又是如何看待时间的？",
      "你曾被我吓了一跳，是在哪里？我们当时分别在做什么？"
    ],
    "描述": "[暂未归档]"
  },
  {
    "名称": "“主角”-基础",
    "原名": "Protagonist",
    "类型": "子职",
    "主职": "时游族",
    "等级": "基础",
    "描述": "- **就位:** 你的希望特性“时差”花费的希望点降低至2。\n- **悖论:** 每场景一次，你的职业特性“时滞”可以改为标记1生命点而非2压力点。"
  },
  {
    "名称": "“主角”-进阶",
    "原名": "Protagonist",
    "类型": "子职",
    "主职": "时游族",
    "等级": "进阶",
    "描述": "逆转: 你知晓因果的法则有时也可以被“逆转”。每局游戏限一次，你可以在一次掷骰前先行决定掷骰的结果（关键成功、希望成功、希望失败、恐惧成功、恐惧失败）并以此结果执行。而后，你开始进行反应掷骰，直至掷骰出你此前决定的结果，期间每进行一次掷骰，你被迫标记1压力点。"
  },
  {
    "名称": "“主角”-精通",
    "原名": "Protagonist",
    "类型": "子职",
    "主职": "时游族",
    "等级": "精通",
    "描述": "信条: 每局游戏限一次，你标记4压力点并设置一个标准倒计时（4）。倒计时持续期间，你记录期间发生的事情。倒计时结束时，你可以标记2生命点若干次，每标记一次，你选择其中一个事件，将其忽略，代表其在时间流中未发生过。你和游戏主持人共同表述时间将如何“修复”被忽略的事件。"
  },
  {
    "名称": "“游客”-基础",
    "原名": "Traveler",
    "类型": "子职",
    "主职": "时游族",
    "等级": "基础",
    "描述": "- **时刻:** 你的希望特性“时差”可额外花费1希望点，使得此次设置的标准倒计时延长至（2）。\n- **自由:** 时空的束缚对你而言没有过多意义。你不受束缚状态的影响。"
  },
  {
    "名称": "“游客”-进阶",
    "原名": "Traveler",
    "类型": "子职",
    "主职": "时游族",
    "等级": "进阶",
    "描述": "会面: 你有一场早已注定的会面。每局游戏限一次，你可以在切换场景时与游戏主持人共同商讨，在下一个场景中你将见到一个怎样的人，而该人物在此之前从未见过你（而你在未来的某个时刻已经见过了ta）。你对该人物进行的交涉获得+1加值。"
  },
  {
    "名称": "“游客”-精通",
    "原名": "Traveler",
    "类型": "子职",
    "主职": "时游族",
    "等级": "精通",
    "描述": "时暮: 你活在时光之中，黄昏时刻无故人。每局游戏限一次，你设置一个标准倒计时（3）。倒计时持续期间，当前场景内除了你之外的所有生物时间暂时停止。倒计时结束时，你立即执行死亡行动。"
  }
]